faststylometry/__init__.py
faststylometry/burrows_delta.py
faststylometry/corpus.py
faststylometry/en.py
faststylometry/examples.py
faststylometry/probability.py
faststylometry/util.py
faststylometry-1.0.4.dist-info/LICENSE
faststylometry-1.0.4.dist-info/METADATA
faststylometry-1.0.4.dist-info/WHEEL
faststylometry-1.0.4.dist-info/top_level.txt
faststylometry-1.0.4.dist-info/RECORD
