Metadata-Version: 2.1
Name: faststylometry
Version: 1.0.4
Summary: Python library for calculating the Burrows Delta.
Home-page: https://fastdatascience.com/fast-stylometry-python-library
Author: Thomas Wood
Author-email: thomas@fastdatascience.com
Project-URL: Documentation, https://fastdatascience.com/fast-stylometry-python-library
Project-URL: Bug Reports, https://github.com/fastdatascience/faststylometry/issues
Project-URL: Source Code, https://github.com/fastdatascience/faststylometry
Keywords: stylometry,nlp,burrows delta,delta,forensic stylometry,natural language processing
Classifier: Development Status :: 5 - Production/Stable
Classifier: Intended Audience :: Developers
Classifier: Topic :: Software Development :: Build Tools
Classifier: Programming Language :: Python :: 3
Classifier: Programming Language :: Python :: 3.6
Classifier: Programming Language :: Python :: 3.7
Classifier: Programming Language :: Python :: 3.8
Classifier: Programming Language :: Python :: 3.9
Classifier: Programming Language :: Python :: 3.10
Classifier: Programming Language :: Python :: 3 :: Only
Classifier: License :: OSI Approved :: MIT License
Classifier: Operating System :: OS Independent
Requires-Python: >=3.6
License-File: LICENSE
Requires-Dist: numpy <=1.24.3,>=1.18
Requires-Dist: pandas <=2.1.0,>=1.5.3
Requires-Dist: scikit-learn <=1.3.0,>=1.2.0
Requires-Dist: wget <4.0,>=3.0
Provides-Extra: dev
Requires-Dist: check-manifest ; extra == 'dev'
